saezo_csv_converter/__init__.py
saezo_csv_converter/converter.py
saezo_csv_converter-0.2.0.dist-info/entry_points.txt
saezo_csv_converter-0.2.0.dist-info/WHEEL
saezo_csv_converter-0.2.0.dist-info/METADATA
saezo_csv_converter-0.2.0.dist-info/RECORD
